djangoldp_circle/__init__.py
djangoldp_circle/admin.py
djangoldp_circle/apps.py
djangoldp_circle/check_integrity.py
djangoldp_circle/djangoldp_urls.py
djangoldp_circle/factories.py
djangoldp_circle/models.py
djangoldp_circle/views.py
djangoldp_circle/locale/de/LC_MESSAGES/django.mo
djangoldp_circle/locale/de/LC_MESSAGES/django.po
djangoldp_circle/locale/en/LC_MESSAGES/django.mo
djangoldp_circle/locale/en/LC_MESSAGES/django.po
djangoldp_circle/locale/es/LC_MESSAGES/django.mo
djangoldp_circle/locale/es/LC_MESSAGES/django.po
djangoldp_circle/locale/fr/LC_MESSAGES/django.mo
djangoldp_circle/locale/fr/LC_MESSAGES/django.po
djangoldp_circle/management/__init__.py
djangoldp_circle/management/commands/__init__.py
djangoldp_circle/management/commands/mock_circle.py
djangoldp_circle/migrations/0001_initial.py
djangoldp_circle/migrations/0002_auto_20191021_1357.py
djangoldp_circle/migrations/0003_auto_20191024_1604.py
djangoldp_circle/migrations/0004_auto_20191024_1831.py
djangoldp_circle/migrations/0005_auto_20191029_1227.py
djangoldp_circle/migrations/0006_circle_status.py
djangoldp_circle/migrations/0007_auto_20191112_1251.py
djangoldp_circle/migrations/0008_circlemember_is_admin.py
djangoldp_circle/migrations/0009_auto_20200226_1742.py
djangoldp_circle/migrations/0010_auto_20200414_0908.py
djangoldp_circle/migrations/0011_auto_20200426_1632.py
djangoldp_circle/migrations/0012_auto_20200427_1047.py
djangoldp_circle/migrations/0013_auto_20200429_1346.py
djangoldp_circle/migrations/0013_auto_20200506_1503.py
djangoldp_circle/migrations/0014_auto_20200501_1207.py
djangoldp_circle/migrations/0014_auto_20200506_1517.py
djangoldp_circle/migrations/0015_auto_20200505_1733.py
djangoldp_circle/migrations/0016_merge_20200506_1904.py
djangoldp_circle/migrations/0017_auto_20200512_1348.py
djangoldp_circle/migrations/0018_auto_20200512_1352.py
djangoldp_circle/migrations/0019_auto_20200522_1516.py
djangoldp_circle/migrations/0020_auto_20200610_1323.py
djangoldp_circle-5.0.0.dist-info/METADATA
djangoldp_circle-5.0.0.dist-info/WHEEL
djangoldp_circle-5.0.0.dist-info/top_level.txt
djangoldp_circle-5.0.0.dist-info/RECORD
