Metadata-Version: 2.4
Name: djangoldp_circle
Version: 5.0.0
Summary: djangoldp package for circle data models
Home-page: https://git.startinblox.com/djangoldp-packages/djangoldp-circle
Author: Startin'blox
Author-email: nicolas@happy-dev.fr
License: MIT
Requires-Dist: djangoldp~=5.0.0
Requires-Dist: djangoldp_account~=5.0.0
Provides-Extra: dev
Requires-Dist: factory_boy>=2.11.0; extra == "dev"
Requires-Dist: djangoldp_notification>=4.0; extra == "dev"
